tg_utils/__init__.py
tg_utils/admin.py
tg_utils/checks.py
tg_utils/compressor_filters.py
tg_utils/decorators.py
tg_utils/email.py
tg_utils/files.py
tg_utils/hashmodels.py
tg_utils/health_check/__init__.py
tg_utils/health_check/base_checks.py
tg_utils/health_check/checks/__init__.py
tg_utils/health_check/checks/celery_beat/__init__.py
tg_utils/health_check/checks/celery_beat/apps.py
tg_utils/health_check/checks/celery_beat/backends.py
tg_utils/health_check/checks/celery_beat/tasks.py
tg_utils/health_check/checks/elvis/__init__.py
tg_utils/health_check/checks/elvis/apps.py
tg_utils/health_check/checks/elvis/backends.py
tg_utils/health_check/checks/phantomjs/__init__.py
tg_utils/health_check/checks/phantomjs/apps.py
tg_utils/health_check/checks/phantomjs/backends.py
tg_utils/health_check/urls.py
tg_utils/health_check/views.py
tg_utils/locale/et/LC_MESSAGES/django.mo
tg_utils/locale/et/LC_MESSAGES/django.po
tg_utils/lock.py
tg_utils/managers.py
tg_utils/mixins.py
tg_utils/models.py
tg_utils/profiling.py
tg_utils/signals.py
tg_utils/templates/admin/edit_inline/no_obj_head/stacked.html
tg_utils/templates/admin/edit_inline/no_obj_head/tabular.html
tg_utils/uuid.py
tg_utils-1.0.2.dist-info/AUTHORS.rst
tg_utils-1.0.2.dist-info/LICENSE
tg_utils-1.0.2.dist-info/METADATA
tg_utils-1.0.2.dist-info/WHEEL
tg_utils-1.0.2.dist-info/RECORD
