Metadata-Version: 2.1
Name: tg-utils
Version: 1.0.2
Summary: Common utils for Django-based projects.
Home-page: https://github.com/thorgate/tg-utils
License: ISCL
Keywords: tg-utils,thorgate
Author: Thorgate
Author-email: code@thorgate.eu
Requires-Python: >=3.7.2,<4
Classifier: Development Status :: 3 - Alpha
Classifier: Framework :: Django
Classifier: Intended Audience :: Developers
Classifier: License :: OSI Approved :: ISC License (ISCL)
Classifier: License :: Other/Proprietary License
Classifier: Natural Language :: English
Classifier: Programming Language :: Python :: 3
Classifier: Programming Language :: Python :: 3.8
Classifier: Programming Language :: Python :: 3.9
Classifier: Programming Language :: Python :: 3.10
Classifier: Programming Language :: Python :: 3.11
Classifier: Programming Language :: Python :: 3.12
Classifier: Programming Language :: Python :: 3.6
Classifier: Programming Language :: Python :: 3.7
Provides-Extra: health-check
Provides-Extra: lock
Provides-Extra: model-hash
Provides-Extra: profiling
Requires-Dist: django (>=2.2)
Requires-Dist: django-health-check ; extra == "health-check"
Requires-Dist: hashids ; extra == "model-hash"
Requires-Dist: psutil ; extra == "health-check"
Requires-Dist: python-redis-lock ; extra == "lock"
Requires-Dist: redis ; extra == "lock"
Requires-Dist: requests ; extra == "health-check"
Requires-Dist: yappi ; extra == "profiling"
Project-URL: Repository, https://github.com/thorgate/tg-utils
